{"paging": {"is_end": false, "totals": 25857, "previous": "https://www.zhihu.com/members/shi-kong-23-21/followers?per_page=20&include=data%5B%2A%5D.answer_count%2Carticles_count%2Cfollower_count%2Cis_followed%2Cis_following%2Cbadge%5B%3F%28type%3Dbest_answerer%29%5D.topics&limit=20&offset=21880", "is_start": false, "next": "https://www.zhihu.com/members/shi-kong-23-21/followers?per_page=20&include=data%5B%2A%5D.answer_count%2Carticles_count%2Cfollower_count%2Cis_followed%2Cis_following%2Cbadge%5B%3F%28type%3Dbest_answerer%29%5D.topics&limit=20&offset=21920"}, "data": [{"is_followed": false, "avatar_url_template": "https://pic1.zhimg.com/da8e974dc_{size}.jpg", "user_type": "people", "answer_count": 1, "is_following": false, "url_token": "san-tian-liang-jiao-36", "id": "9766e66124c1cdffc26efbbe85b08c5d", "articles_count": 0, "name": "\u4e09\u751c\u4e24\u8549", "is_advertiser": false, "url": "https://www.zhihu.com/people/9766e66124c1cdffc26efbbe85b08c5d", "type": "people", "vip_info": {"is_vip": false}, "headline": "", "avatar_url": "https://pic1.zhimg.com/da8e974dc_is.jpg", "is_org": false, "gender": -1, "follower_count": 0, "badge": []}, {"is_followed": false, "avatar_url_template": "https://pic4.zhimg.com/v2-7b4d23e55f08c18b16e0bf1db742db3f_{size}.jpg", "user_type": "people", "answer_count": 58, "is_following": false, "url_token": "qing-jin-52-27", "id": "d4b5d1b7cbb601d614045dfcc62768b4", "articles_count": 0, "name": "\u4ed9\u9e64\u9e64\u9e64", "is_advertiser": false, "url": "https://www.zhihu.com/people/d4b5d1b7cbb601d614045dfcc62768b4", "type": "people", "vip_info": {"is_vip": false}, "headline": "", "avatar_url": "https://pic4.zhimg.com/v2-7b4d23e55f08c18b16e0bf1db742db3f_is.jpg", "is_org": false, "gender": -1, "follower_count": 2, "badge": []}, {"is_followed": false, "avatar_url_template": "https://pic3.zhimg.com/v2-6a142d7f5f70c03ea824fdfb55e9a436_{size}.jpg", "user_type": "people", "answer_count": 41, "is_following": false, "url_token": "luo-xiao-tong-62-8", "id": "b7dfa1d1aaf49fd841f48de9aacc8a18", "articles_count": 0, "name": "\u7f57\u5c0f\u901a", "is_advertiser": false, "url": "https://www.zhihu.com/people/b7dfa1d1aaf49fd841f48de9aacc8a18", "type": "people", "vip_info": {"is_vip": false}, "headline": "\u5b66\u751f", "avatar_url": "https://pic3.zhimg.com/v2-6a142d7f5f70c03ea824fdfb55e9a436_is.jpg", "is_org": false, "gender": -1, "follower_count": 4, "badge": []}, {"is_followed": false, "avatar_url_template": "https://pic1.zhimg.com/da8e974dc_{size}.jpg", "user_type": "people", "answer_count": 10, "is_following": false, "url_token": "feng-kuang-de-da-ke-ai", "id": "16b7dab63016207c0f3148f97ca4ca1b", "articles_count": 0, "name": "\u7f8eLV\u5b50", "is_advertiser": false, "url": "https://www.zhihu.com/people/16b7dab63016207c0f3148f97ca4ca1b", "type": "people", "vip_info": {"is_vip": false}, "headline": "", "avatar_url": "https://pic1.zhimg.com/da8e974dc_is.jpg", "is_org": false, "gender": 0, "follower_count": 0, "badge": []}, {"is_followed": false, "avatar_url_template": "https://pic1.zhimg.com/da8e974dc_{size}.jpg", "user_type": "people", "answer_count": 0, "is_following": false, "url_token": "xiao-xiao-xiao-hao-38-70", "id": "4bbcb07901b15f07a821fbbe21c46090", "articles_count": 0, "name": "\u5c0f\u5c0f\u5c0f\u53f7", "is_advertiser": false, "url": "https://www.zhihu.com/people/4bbcb07901b15f07a821fbbe21c46090", "type": "people", "vip_info": {"is_vip": false}, "headline": "\u5927\u5b66\u751f", "avatar_url": "https://pic1.zhimg.com/da8e974dc_is.jpg", "is_org": false, "gender": -1, "follower_count": 0, "badge": []}, {"is_followed": false, "avatar_url_template": "https://pic1.zhimg.com/v2-592c9ef9aceb5591fc0e158b7dedcf34_{size}.jpg", "user_type": "people", "answer_count": 6, "is_following": false, "url_token": "mang-mang-97-98", "id": "14dfaed76cb6aa84c244e6739570bd93", "articles_count": 0, "name": "\u832b\u832b", "is_advertiser": false, "url": "https://www.zhihu.com/people/14dfaed76cb6aa84c244e6739570bd93", "type": "people", "vip_info": {"is_vip": false}, "headline": "", "avatar_url": "https://pic1.zhimg.com/v2-592c9ef9aceb5591fc0e158b7dedcf34_is.jpg", "is_org": false, "gender": -1, "follower_count": 0, "badge": []}, {"is_followed": false, "avatar_url_template": "https://pic2.zhimg.com/v2-3c7a5dde4a175e0b3481104a270d64ad_{size}.jpg", "user_type": "people", "answer_count": 56, "is_following": false, "url_token": "jiu-shi-jiu-xing-jiang-62", "id": "632ccea3a3cc9288a4394db9fd462804", "articles_count": 35, "name": "\u5b89\u6c38\u900f", "is_advertiser": false, "url": "https://www.zhihu.com/people/632ccea3a3cc9288a4394db9fd462804", "type": "people", "vip_info": {"is_vip": false}, "headline": "\u4e18\u5893\u853d\u5c71\u5ca1\uff0c\u842c\u4ee3\u540c\u4e00\u6642", "avatar_url": "https://pic2.zhimg.com/v2-3c7a5dde4a175e0b3481104a270d64ad_is.jpg", "is_org": false, "gender": -1, "follower_count": 419, "badge": []}, {"is_followed": false, "avatar_url_template": "https://pic4.zhimg.com/v2-40796e3d4337a228f8a88ceb80277397_{size}.jpg", "user_type": "people", "answer_count": 3, "is_following": false, "url_token": "xbc-85", "id": "61ed64cbec03cef04d32e123a1dafe9a", "articles_count": 0, "name": "xbc", "is_advertiser": false, "url": "https://www.zhihu.com/people/61ed64cbec03cef04d32e123a1dafe9a", "type": "people", "vip_info": {"is_vip": false}, "headline": "", "avatar_url": "https://pic4.zhimg.com/v2-40796e3d4337a228f8a88ceb80277397_is.jpg", "is_org": false, "gender": -1, "follower_count": 1, "badge": []}, {"is_followed": false, "avatar_url_template": "https://pic4.zhimg.com/v2-139d517a46a1b055a0258dd0d6522437_{size}.jpg", "user_type": "people", "answer_count": 3, "is_following": false, "url_token": "ta-do-42", "id": "620c03a12e1c8a1cc313caa1aa079250", "articles_count": 0, "name": "Nekoyomi", "is_advertiser": false, "url": "https://www.zhihu.com/people/620c03a12e1c8a1cc313caa1aa079250", "type": "people", "vip_info": {"is_vip": false}, "headline": "I LOVE MEMES.", "avatar_url": "https://pic4.zhimg.com/v2-139d517a46a1b055a0258dd0d6522437_is.jpg", "is_org": false, "gender": 1, "follower_count": 20, "badge": []}, {"is_followed": false, "avatar_url_template": "https://pic4.zhimg.com/v2-9597c00607eb0c4e7960bc94e6b4b607_{size}.jpg", "user_type": "people", "answer_count": 4, "is_following": false, "url_token": "zhe-ye-66-35-30", "id": "c62fe81912d64210650f62ea23bb08cd", "articles_count": 0, "name": "\u8d30\u5341\u9646beats", "is_advertiser": false, "url": "https://www.zhihu.com/people/c62fe81912d64210650f62ea23bb08cd", "type": "people", "vip_info": {"is_vip": false}, "headline": "Feel alive", "avatar_url": "https://pic4.zhimg.com/v2-9597c00607eb0c4e7960bc94e6b4b607_is.jpg", "is_org": false, "gender": 0, "follower_count": 12, "badge": []}, {"is_followed": false, "avatar_url_template": "https://pic1.zhimg.com/da8e974dc_{size}.jpg", "user_type": "people", "answer_count": 2, "is_following": false, "url_token": "gou-shu-86-47", "id": "30547234bc9ea247a5fd8cadf1e20951", "articles_count": 0, "name": "\u72d7\u53d4", "is_advertiser": false, "url": "https://www.zhihu.com/people/30547234bc9ea247a5fd8cadf1e20951", "type": "people", "vip_info": {"is_vip": false}, "headline": "", "avatar_url": "https://pic1.zhimg.com/da8e974dc_is.jpg", "is_org": false, "gender": -1, "follower_count": 0, "badge": []}, {"is_followed": false, "avatar_url_template": "https://pic3.zhimg.com/5b44303e05af9279418b286f5bf60156_{size}.jpg", "user_type": "people", "answer_count": 6, "is_following": false, "url_token": "setsuna-73", "id": "9610747ade14f5ffd2328cf2a8f39b24", "articles_count": 0, "name": "Setsuna", "is_advertiser": false, "url": "https://www.zhihu.com/people/9610747ade14f5ffd2328cf2a8f39b24", "type": "people", "vip_info": {"is_vip": false}, "headline": "\u6444\u5f71/HiFi/\u5e94\u7528\u5fc3\u7406\u5b66\u672c\u79d1\u5728\u8bfb", "avatar_url": "https://pic3.zhimg.com/5b44303e05af9279418b286f5bf60156_is.jpg", "is_org": false, "gender": 1, "follower_count": 7, "badge": []}, {"is_followed": false, "avatar_url_template": "https://pic4.zhimg.com/v2-d07b46c5dd224b3bc11770471eb6afeb_{size}.jpg", "user_type": "people", "answer_count": 6, "is_following": false, "url_token": "zhou-zi-hao-4-66", "id": "9357037d6090a6ff58b0fe3261e38f52", "articles_count": 0, "name": "\u5b89\u4f2f\u5c18", "is_advertiser": false, "url": "https://www.zhihu.com/people/9357037d6090a6ff58b0fe3261e38f52", "type": "people", "vip_info": {"is_vip": false}, "headline": "\u5251\u4e09", "avatar_url": "https://pic4.zhimg.com/v2-d07b46c5dd224b3bc11770471eb6afeb_is.jpg", "is_org": false, "gender": -1, "follower_count": 1, "badge": []}, {"is_followed": false, "avatar_url_template": "https://pic2.zhimg.com/v2-f01c76ac3c41e2d08f809d663b688a55_{size}.jpg", "user_type": "people", "answer_count": 2, "is_following": false, "url_token": "wyl-99-51", "id": "ecc6ace4a6cf85f95dc67009b11fa5db", "articles_count": 0, "name": "\u53ef\u54b8\u53ef\u751c\u5c11\u5973", "is_advertiser": false, "url": "https://www.zhihu.com/people/ecc6ace4a6cf85f95dc67009b11fa5db", "type": "people", "vip_info": {"is_vip": false}, "headline": "", "avatar_url": "https://pic2.zhimg.com/v2-f01c76ac3c41e2d08f809d663b688a55_is.jpg", "is_org": false, "gender": 0, "follower_count": 0, "badge": []}, {"is_followed": false, "avatar_url_template": "https://pic4.zhimg.com/d9acb1b51176d366e1d26b78054d838b_{size}.jpg", "user_type": "people", "answer_count": 23, "is_following": false, "url_token": "liu-yue-liu-yue-67", "id": "c29f36c4d0b24fb55cd3c29d7a8ecfce", "articles_count": 0, "name": "\u4e00\u53ea\u7279\u7acb\u72ec\u884c\u7684\u72d7", "is_advertiser": false, "url": "https://www.zhihu.com/people/c29f36c4d0b24fb55cd3c29d7a8ecfce", "type": "people", "vip_info": {"is_vip": false}, "headline": "", "avatar_url": "https://pic4.zhimg.com/d9acb1b51176d366e1d26b78054d838b_is.jpg", "is_org": false, "gender": 0, "follower_count": 5, "badge": []}, {"is_followed": false, "avatar_url_template": "https://pic1.zhimg.com/v2-e346d2f95bb006fa332dcdad7b67fef8_{size}.jpg", "user_type": "people", "answer_count": 0, "is_following": false, "url_token": "shen-jian-46-13", "id": "dc9c5d5935b6966ff44bb325335b12fb", "articles_count": 0, "name": "\u5206\u679d\u5b9a\u754c", "is_advertiser": false, "url": "https://www.zhihu.com/people/dc9c5d5935b6966ff44bb325335b12fb", "type": "people", "vip_info": {"is_vip": false}, "headline": "\u60f3\u91cd\u65b0\u6210\u719f\u4e00\u904d\u7684\u5b69\u5b50", "avatar_url": "https://pic1.zhimg.com/v2-e346d2f95bb006fa332dcdad7b67fef8_is.jpg", "is_org": false, "gender": -1, "follower_count": 0, "badge": []}, {"is_followed": false, "avatar_url_template": "https://pic3.zhimg.com/v2-f449e13a52e4b353c57f3779874f786e_{size}.jpg", "user_type": "people", "answer_count": 6, "is_following": false, "url_token": "YangFan--13", "id": "4d32f1e689c032d650967b8fa17cc616", "articles_count": 0, "name": "\u4e8e\u6c38\u6ce2", "is_advertiser": false, "url": "https://www.zhihu.com/people/4d32f1e689c032d650967b8fa17cc616", "type": "people", "vip_info": {"is_vip": false}, "headline": "\u7cbe\u795e\u4f0a\u6717\u4eba\uff08\u8feb\u771f\uff09", "avatar_url": "https://pic3.zhimg.com/v2-f449e13a52e4b353c57f3779874f786e_is.jpg", "is_org": false, "gender": -1, "follower_count": 3, "badge": []}, {"is_followed": false, "avatar_url_template": "https://pic2.zhimg.com/04e6021063598a0ac5991b9aaa1818d9_{size}.jpg", "user_type": "people", "answer_count": 0, "is_following": false, "url_token": "goroan", "id": "eb077e38e02dd4115daac36a02208962", "articles_count": 0, "name": "Goroan", "is_advertiser": false, "url": "https://www.zhihu.com/people/eb077e38e02dd4115daac36a02208962", "type": "people", "vip_info": {"is_vip": false}, "headline": "", "avatar_url": "https://pic2.zhimg.com/04e6021063598a0ac5991b9aaa1818d9_is.jpg", "is_org": false, "gender": -1, "follower_count": 1, "badge": []}, {"is_followed": false, "avatar_url_template": "https://pic4.zhimg.com/v2-7b45006f471a35770bc70c9d408e1e6b_{size}.jpg", "user_type": "people", "answer_count": 13, "is_following": false, "url_token": "xiao-na-zha-78", "id": "5653ada16e64b23de149970c3e167fc9", "articles_count": 0, "name": "\u5927\u5c71\u7684\u5b50\u5b59", "is_advertiser": false, "url": "https://www.zhihu.com/people/5653ada16e64b23de149970c3e167fc9", "type": "people", "vip_info": {"is_vip": false}, "headline": "\u61d2\u6563\u7684\u6d6a\u6f2b\u4e3b\u4e49\u8005", "avatar_url": "https://pic4.zhimg.com/v2-7b45006f471a35770bc70c9d408e1e6b_is.jpg", "is_org": false, "gender": 0, "follower_count": 16, "badge": []}, {"is_followed": false, "avatar_url_template": "https://pic1.zhimg.com/da8e974dc_{size}.jpg", "user_type": "people", "answer_count": 2, "is_following": false, "url_token": "nightsnow-18", "id": "75f08abf21389d988dd6968ee1d69fdc", "articles_count": 0, "name": "Nightsnow", "is_advertiser": false, "url": "https://www.zhihu.com/people/75f08abf21389d988dd6968ee1d69fdc", "type": "people", "vip_info": {"is_vip": false}, "headline": "\u5b66\u751f\u3002", "avatar_url": "https://pic1.zhimg.com/da8e974dc_is.jpg", "is_org": false, "gender": -1, "follower_count": 0, "badge": []}]}