{"paging": {"is_end": false, "totals": 25832, "previous": "https://www.zhihu.com/members/shi-kong-23-21/followers?per_page=20&include=data%5B%2A%5D.answer_count%2Carticles_count%2Cfollower_count%2Cis_followed%2Cis_following%2Cbadge%5B%3F%28type%3Dbest_answerer%29%5D.topics&limit=20&offset=200", "is_start": false, "next": "https://www.zhihu.com/members/shi-kong-23-21/followers?per_page=20&include=data%5B%2A%5D.answer_count%2Carticles_count%2Cfollower_count%2Cis_followed%2Cis_following%2Cbadge%5B%3F%28type%3Dbest_answerer%29%5D.topics&limit=20&offset=240"}, "data": [{"is_followed": false, "avatar_url_template": "https://pic3.zhimg.com/v2-0b374689649cbec81b911654c3feafaa_{size}.jpg", "user_type": "people", "answer_count": 23, "is_following": false, "url_token": "su-lian-20050525", "id": "cf0d286e31d8c46c2ac82e1e7cc75334", "articles_count": 1, "name": "\u82cf\u6f4b", "is_advertiser": false, "url": "https://www.zhihu.com/people/cf0d286e31d8c46c2ac82e1e7cc75334", "type": "people", "vip_info": {"is_vip": false}, "headline": "ENTP / MUNer", "avatar_url": "https://pic3.zhimg.com/v2-0b374689649cbec81b911654c3feafaa_is.jpg", "is_org": false, "gender": 0, "follower_count": 6, "badge": []}, {"is_followed": false, "avatar_url_template": "https://pic2.zhimg.com/v2-753bdfc1bb06dd5cd57add00c1639f11_{size}.jpg", "user_type": "people", "answer_count": 9, "is_following": false, "url_token": "sun-hao-yu-0113", "id": "fd0e8791435922f0548d5ab8f0cb8d3b", "articles_count": 0, "name": "\u7cd6\u7092\u6817\u5b50\u9c7c", "is_advertiser": false, "url": "https://www.zhihu.com/people/fd0e8791435922f0548d5ab8f0cb8d3b", "type": "people", "vip_info": {"is_vip": false}, "headline": "\u6211\u7684\u4f53\u91cd\u7ec8\u4e8e\u548c\u6211\u7684\u8eab\u9ad8\u6253\u6210\u4e86\u5e73\u624b", "avatar_url": "https://pic2.zhimg.com/v2-753bdfc1bb06dd5cd57add00c1639f11_is.jpg", "is_org": false, "gender": -1, "follower_count": 6, "badge": []}, {"is_followed": false, "avatar_url_template": "https://pic3.zhimg.com/7b4a5ecd59c21e03226390356f69f522_{size}.jpg", "user_type": "people", "answer_count": 3, "is_following": false, "url_token": "cao-jin-rui-21", "id": "48eb5eece84b810247f5332b3821b8fe", "articles_count": 0, "name": "Saturnus", "is_advertiser": false, "url": "https://www.zhihu.com/people/48eb5eece84b810247f5332b3821b8fe", "type": "people", "vip_info": {"is_vip": false}, "headline": "\u5173\u5c71\u96be\u8d8a\uff0c\u8c01\u60b2\u5931\u8def\u4e4b\u4eba\uff1b\u840d\u6c34\u76f8\u9022\uff0c\u5c3d\u662f\u4ed6\u4e61\u4e4b\u5ba2\u3002", "avatar_url": "https://pic3.zhimg.com/7b4a5ecd59c21e03226390356f69f522_is.jpg", "is_org": false, "gender": 1, "follower_count": 6, "badge": []}, {"is_followed": false, "avatar_url_template": "https://pic2.zhimg.com/v2-f262a0a53068f655897255558ed5cd11_{size}.jpg", "user_type": "people", "answer_count": 1, "is_following": false, "url_token": "zyw-3-66", "id": "4a59effbbab19a53723caab2c15503a9", "articles_count": 0, "name": "zyw", "is_advertiser": false, "url": "https://www.zhihu.com/people/4a59effbbab19a53723caab2c15503a9", "type": "people", "vip_info": {"is_vip": false}, "headline": "", "avatar_url": "https://pic2.zhimg.com/v2-f262a0a53068f655897255558ed5cd11_is.jpg", "is_org": false, "gender": -1, "follower_count": 0, "badge": []}, {"is_followed": false, "avatar_url_template": "https://pic2.zhimg.com/v2-bf06443d77bc04b91bd12a61c59f5f4d_{size}.jpg", "user_type": "people", "answer_count": 0, "is_following": false, "url_token": "song-zi-77-60", "id": "1f1a5ff7e55373178d07e209aad092d0", "articles_count": 0, "name": "Daniel", "is_advertiser": false, "url": "https://www.zhihu.com/people/1f1a5ff7e55373178d07e209aad092d0", "type": "people", "vip_info": {"is_vip": false}, "headline": "\u51b7\u773c\u89c2\u6f6e", "avatar_url": "https://pic2.zhimg.com/v2-bf06443d77bc04b91bd12a61c59f5f4d_is.jpg", "is_org": false, "gender": -1, "follower_count": 0, "badge": []}, {"is_followed": false, "avatar_url_template": "https://pic1.zhimg.com/v2-7963c133f0712c78db5a8b3b075cea7c_{size}.jpg", "user_type": "people", "answer_count": 0, "is_following": false, "url_token": "zhou-zi-da-15", "id": "430c045fe10d830cc54ea32fcfcc43ce", "articles_count": 0, "name": "\u5468\u5b50\u8fbe", "is_advertiser": false, "url": "https://www.zhihu.com/people/430c045fe10d830cc54ea32fcfcc43ce", "type": "people", "vip_info": {"is_vip": false}, "headline": "\u5b66\u751f\uff0c\u6587\u5b66\uff0c\u7535\u5f71", "avatar_url": "https://pic1.zhimg.com/v2-7963c133f0712c78db5a8b3b075cea7c_is.jpg", "is_org": false, "gender": -1, "follower_count": 0, "badge": []}, {"is_followed": false, "avatar_url_template": "https://pic4.zhimg.com/v2-b56af35431d170a1743910d2b507c6af_{size}.jpg", "user_type": "people", "answer_count": 0, "is_following": false, "url_token": "nan-fang-gu-niang-7-83", "id": "75596985a356c9b014c0c98cfe3f85a5", "articles_count": 0, "name": "\u9999\u53f6", "is_advertiser": false, "url": "https://www.zhihu.com/people/75596985a356c9b014c0c98cfe3f85a5", "type": "people", "vip_info": {"is_vip": false}, "headline": "\u5b66\u751f", "avatar_url": "https://pic4.zhimg.com/v2-b56af35431d170a1743910d2b507c6af_is.jpg", "is_org": false, "gender": 0, "follower_count": 1, "badge": []}, {"is_followed": false, "avatar_url_template": "https://pic4.zhimg.com/v2-22a398580fe23589e43ee969e61094af_{size}.jpg", "user_type": "people", "answer_count": 2, "is_following": false, "url_token": "bao-bao-48-73-9", "id": "2ad31c09a9db24a8124c39dc3a4eceda", "articles_count": 0, "name": "\u6211\u5154\u53ef\u7231\u70b8\u4e86", "is_advertiser": false, "url": "https://www.zhihu.com/people/2ad31c09a9db24a8124c39dc3a4eceda", "type": "people", "vip_info": {"is_vip": false}, "headline": "", "avatar_url": "https://pic4.zhimg.com/v2-22a398580fe23589e43ee969e61094af_is.jpg", "is_org": false, "gender": -1, "follower_count": 0, "badge": []}, {"is_followed": false, "avatar_url_template": "https://pic3.zhimg.com/v2-c356ce619cdb0896c161b8e28b69348a_{size}.jpg", "user_type": "people", "answer_count": 1, "is_following": false, "url_token": "jiang-nan-de-yan-yu-96", "id": "9521b5a79aafdce23bf53d0908182617", "articles_count": 0, "name": "\u6c5f\u5357\u540c\u5b66\u5440", "is_advertiser": false, "url": "https://www.zhihu.com/people/9521b5a79aafdce23bf53d0908182617", "type": "people", "vip_info": {"is_vip": false}, "headline": "\u609f\u5df2\u5f80\u4e4b\u4e0d\u8c0f\uff0c\u77e5\u6765\u8005\u4e4b\u53ef\u8ffd\u3002", "avatar_url": "https://pic3.zhimg.com/v2-c356ce619cdb0896c161b8e28b69348a_is.jpg", "is_org": false, "gender": -1, "follower_count": 2, "badge": []}, {"is_followed": false, "avatar_url_template": "https://pic4.zhimg.com/v2-7f3f45ac8c490cead11d49e2c5d2aa23_{size}.jpg", "user_type": "people", "answer_count": 16, "is_following": false, "url_token": "lou-xia-xiao-hei-34", "id": "47b736c38a538c5fedb85da060358b2a", "articles_count": 0, "name": "\u697c\u4e0b\u5c0f\u9ed1", "is_advertiser": false, "url": "https://www.zhihu.com/people/47b736c38a538c5fedb85da060358b2a", "type": "people", "vip_info": {"is_vip": false}, "headline": "\u8ffd\u5149\u8005", "avatar_url": "https://pic4.zhimg.com/v2-7f3f45ac8c490cead11d49e2c5d2aa23_is.jpg", "is_org": false, "gender": 1, "follower_count": 6, "badge": []}, {"is_followed": false, "avatar_url_template": "https://pic4.zhimg.com/v2-4b7008d731aa745f3e677d70b7713677_{size}.jpg", "user_type": "people", "answer_count": 1, "is_following": false, "url_token": "preciousd", "id": "5544d4eaba2982c8814d20cd51f700e2", "articles_count": 0, "name": "PreciousD", "is_advertiser": false, "url": "https://www.zhihu.com/people/5544d4eaba2982c8814d20cd51f700e2", "type": "people", "vip_info": {"is_vip": false}, "headline": "\u4e00\u53ea\u5927\u4e8c\u7684\u4f1a\u8ba1\u5b66\u7cfb\u5c0f\u767d", "avatar_url": "https://pic4.zhimg.com/v2-4b7008d731aa745f3e677d70b7713677_is.jpg", "is_org": false, "gender": -1, "follower_count": 0, "badge": []}, {"is_followed": false, "avatar_url_template": "https://pic1.zhimg.com/da8e974dc_{size}.jpg", "user_type": "people", "answer_count": 2, "is_following": false, "url_token": "qian-rui-xiang", "id": "12850df14708eb2f3f4de3a4e934ce2d", "articles_count": 0, "name": "\u7231\u5531\u6b4c\u4f1a\u5356\u840c\u7684\u94b1", "is_advertiser": false, "url": "https://www.zhihu.com/people/12850df14708eb2f3f4de3a4e934ce2d", "type": "people", "vip_info": {"is_vip": false}, "headline": "\u5b66\u751f", "avatar_url": "https://pic1.zhimg.com/da8e974dc_is.jpg", "is_org": false, "gender": -1, "follower_count": 2, "badge": []}, {"is_followed": false, "avatar_url_template": "https://pic2.zhimg.com/v2-3135c2a24528d08df6717c799c193e4d_{size}.jpg", "user_type": "people", "answer_count": 12, "is_following": false, "url_token": "nei-han-gou-yi-zhi", "id": "3bc3374b90daf0203b877bc68871367d", "articles_count": 0, "name": "\u6811\u6811\u6811", "is_advertiser": false, "url": "https://www.zhihu.com/people/3bc3374b90daf0203b877bc68871367d", "type": "people", "vip_info": {"is_vip": false}, "headline": "\u5355\u8eab\u72d7\u4e00\u53ea \u6ca1\u4ec0\u4e48\u597d\u63cf\u8ff0\u7684", "avatar_url": "https://pic2.zhimg.com/v2-3135c2a24528d08df6717c799c193e4d_is.jpg", "is_org": false, "gender": 1, "follower_count": 2, "badge": []}, {"is_followed": false, "avatar_url_template": "https://pic3.zhimg.com/v2-0677126d5a9381b3219c41ddef9f9b56_{size}.jpg", "user_type": "people", "answer_count": 62, "is_following": false, "url_token": "le-wa-33-24", "id": "ce06898c89deac731d9f2b50a5c9cd4b", "articles_count": 0, "name": "\u67ef\u7f57\u4f0a", "is_advertiser": false, "url": "https://www.zhihu.com/people/ce06898c89deac731d9f2b50a5c9cd4b", "type": "people", "vip_info": {"is_vip": false}, "headline": "", "avatar_url": "https://pic3.zhimg.com/v2-0677126d5a9381b3219c41ddef9f9b56_is.jpg", "is_org": false, "gender": -1, "follower_count": 7, "badge": []}, {"is_followed": false, "avatar_url_template": "https://pic4.zhimg.com/v2-a3a31ccd72709679426492833abd5b03_{size}.jpg", "user_type": "people", "answer_count": 0, "is_following": false, "url_token": "li-chen-hao-47-65", "id": "34e1027a2bd0d9886864f464f165ab38", "articles_count": 0, "name": "Messia", "is_advertiser": false, "url": "https://www.zhihu.com/people/34e1027a2bd0d9886864f464f165ab38", "type": "people", "vip_info": {"is_vip": false}, "headline": "\u5b66\u751f", "avatar_url": "https://pic4.zhimg.com/v2-a3a31ccd72709679426492833abd5b03_is.jpg", "is_org": false, "gender": -1, "follower_count": 1, "badge": []}, {"is_followed": false, "avatar_url_template": "https://pic1.zhimg.com/v2-28489e618db656167dadf4d7f3d72254_{size}.jpg", "user_type": "people", "answer_count": 0, "is_following": false, "url_token": "ye-yu-sheng-fan-37-33", "id": "388b312e26bf1df06408aba57580c0e6", "articles_count": 0, "name": "\u591c\u96e8\u58f0\u70e6", "is_advertiser": false, "url": "https://www.zhihu.com/people/388b312e26bf1df06408aba57580c0e6", "type": "people", "vip_info": {"is_vip": false}, "headline": "", "avatar_url": "https://pic1.zhimg.com/v2-28489e618db656167dadf4d7f3d72254_is.jpg", "is_org": false, "gender": 0, "follower_count": 12, "badge": []}, {"is_followed": false, "avatar_url_template": "https://pic1.zhimg.com/da8e974dc_{size}.jpg", "user_type": "people", "answer_count": 1, "is_following": false, "url_token": "yi-ran-shi-yi-yue", "id": "26ccda5fa7145aa8f280a1975bbee3c9", "articles_count": 0, "name": "\u4f9d\u7136\u5341\u4e00\u6708", "is_advertiser": false, "url": "https://www.zhihu.com/people/26ccda5fa7145aa8f280a1975bbee3c9", "type": "people", "vip_info": {"is_vip": false}, "headline": "", "avatar_url": "https://pic1.zhimg.com/da8e974dc_is.jpg", "is_org": false, "gender": -1, "follower_count": 0, "badge": []}, {"is_followed": false, "avatar_url_template": "https://pic1.zhimg.com/v2-70e7a00ecb12beefbc0bedea45d8b974_{size}.jpg", "user_type": "people", "answer_count": 0, "is_following": false, "url_token": "lei-yu-51-51", "id": "bc455493eb0c78616a355debcddc6ba3", "articles_count": 0, "name": "\u5b64\u9171 \u6211\u6ca1\u6709\u732b\u4e86", "is_advertiser": false, "url": "https://www.zhihu.com/people/bc455493eb0c78616a355debcddc6ba3", "type": "people", "vip_info": {"is_vip": false}, "headline": "", "avatar_url": "https://pic1.zhimg.com/v2-70e7a00ecb12beefbc0bedea45d8b974_is.jpg", "is_org": false, "gender": -1, "follower_count": 0, "badge": []}, {"is_followed": false, "avatar_url_template": "https://pic2.zhimg.com/v2-0d1e0568cb986287a63354d45c0caa61_{size}.jpg", "user_type": "people", "answer_count": 6, "is_following": false, "url_token": "huo-xian-sheng-78-15", "id": "82830db2e441beb744ebfcff4378115b", "articles_count": 0, "name": "\u970d\u970dcr", "is_advertiser": false, "url": "https://www.zhihu.com/people/82830db2e441beb744ebfcff4378115b", "type": "people", "vip_info": {"is_vip": false}, "headline": "\u5168\u5c4b\u5b9a\u5236\u5b66\u5458", "avatar_url": "https://pic2.zhimg.com/v2-0d1e0568cb986287a63354d45c0caa61_is.jpg", "is_org": false, "gender": -1, "follower_count": 1, "badge": []}, {"is_followed": false, "avatar_url_template": "https://pic2.zhimg.com/v2-e8dcdd272eb32ad9712bf26498cee349_{size}.jpg", "user_type": "people", "answer_count": 2, "is_following": false, "url_token": "king23-25", "id": "89a01715c1741966fa9233638c5dcc79", "articles_count": 0, "name": "King23", "is_advertiser": false, "url": "https://www.zhihu.com/people/89a01715c1741966fa9233638c5dcc79", "type": "people", "vip_info": {"is_vip": false}, "headline": "\u673a\u68b0\u7535\u5b50\u5de5\u7a0b", "avatar_url": "https://pic2.zhimg.com/v2-e8dcdd272eb32ad9712bf26498cee349_is.jpg", "is_org": false, "gender": -1, "follower_count": 0, "badge": []}]}