{"paging": {"is_end": false, "totals": 25842, "previous": "https://www.zhihu.com/members/shi-kong-23-21/followers?per_page=20&include=data%5B%2A%5D.answer_count%2Carticles_count%2Cfollower_count%2Cis_followed%2Cis_following%2Cbadge%5B%3F%28type%3Dbest_answerer%29%5D.topics&limit=20&offset=6680", "is_start": false, "next": "https://www.zhihu.com/members/shi-kong-23-21/followers?per_page=20&include=data%5B%2A%5D.answer_count%2Carticles_count%2Cfollower_count%2Cis_followed%2Cis_following%2Cbadge%5B%3F%28type%3Dbest_answerer%29%5D.topics&limit=20&offset=6720"}, "data": [{"is_followed": false, "avatar_url_template": "https://pic2.zhimg.com/v2-9bf0fd725277fae492c2d5e939e79145_{size}.jpg", "user_type": "people", "answer_count": 0, "is_following": false, "headline": "", "url_token": "ji-zhi-29-87", "id": "1fb65cc83c0c28763d96149efd301603", "articles_count": 0, "type": "people", "name": "\u59ec\u667a", "url": "https://www.zhihu.com/people/1fb65cc83c0c28763d96149efd301603", "gender": 0, "vip_info": {"is_vip": false}, "is_advertiser": false, "avatar_url": "https://pic2.zhimg.com/v2-9bf0fd725277fae492c2d5e939e79145_is.jpg", "is_org": false, "follower_count": 1, "badge": []}, {"is_followed": false, "avatar_url_template": "https://pic3.zhimg.com/v2-fa4107138de45ca3849a46cb3826cbde_{size}.jpg", "user_type": "people", "answer_count": 0, "is_following": false, "headline": "\u9ad8\u4e2d\u751f", "url_token": "stitches-69", "id": "8002f274551ac82dcee19e02cd5b0642", "articles_count": 0, "type": "people", "name": "\u6211\u6709\u4e09\u4ea9\u5730", "url": "https://www.zhihu.com/people/8002f274551ac82dcee19e02cd5b0642", "gender": -1, "vip_info": {"is_vip": false}, "is_advertiser": false, "avatar_url": "https://pic3.zhimg.com/v2-fa4107138de45ca3849a46cb3826cbde_is.jpg", "is_org": false, "follower_count": 0, "badge": []}, {"is_followed": false, "avatar_url_template": "https://pic2.zhimg.com/v2-22545acced5acaeb811937fd6c584409_{size}.jpg", "user_type": "people", "answer_count": 1, "is_following": false, "headline": "", "url_token": "zhe-li-you-ba-98k", "id": "d6d99522416308656ec703f199048f7f", "articles_count": 0, "type": "people", "name": "\u8fd9\u91cc\u6709\u628a98k", "url": "https://www.zhihu.com/people/d6d99522416308656ec703f199048f7f", "gender": -1, "vip_info": {"is_vip": false}, "is_advertiser": false, "avatar_url": "https://pic2.zhimg.com/v2-22545acced5acaeb811937fd6c584409_is.jpg", "is_org": false, "follower_count": 0, "badge": []}, {"is_followed": false, "avatar_url_template": "https://pic2.zhimg.com/v2-b4ce8a30a68fde4f6f4e60836b8ae021_{size}.jpg", "user_type": "people", "answer_count": 7, "is_following": false, "headline": "\u753b\u6e23", "url_token": "ao-li-ao-li-ao-jiang", "id": "fb6b94bd5373a516c4cd095ac58f0614", "articles_count": 0, "type": "people", "name": "\u91ce\u86ee\u8f6f\u5f31", "url": "https://www.zhihu.com/people/fb6b94bd5373a516c4cd095ac58f0614", "gender": 0, "vip_info": {"is_vip": false}, "is_advertiser": false, "avatar_url": "https://pic2.zhimg.com/v2-b4ce8a30a68fde4f6f4e60836b8ae021_is.jpg", "is_org": false, "follower_count": 0, "badge": []}, {"is_followed": false, "avatar_url_template": "https://pic3.zhimg.com/v2-7c77ba401add01bca365916d34dc0622_{size}.jpg", "user_type": "people", "answer_count": 7, "is_following": false, "headline": "\u77e5\u4e4e\u6700\u5f31\u6c42\u77e5\u8005", "url_token": "1xue-hua-bin-fen-1", "id": "cd3cd86ccbee90a01b2bd1629ffc97c3", "articles_count": 0, "type": "people", "name": "1\u96ea\u82b1\u7f24\u7eb71", "url": "https://www.zhihu.com/people/cd3cd86ccbee90a01b2bd1629ffc97c3", "gender": -1, "vip_info": {"is_vip": false}, "is_advertiser": false, "avatar_url": "https://pic3.zhimg.com/v2-7c77ba401add01bca365916d34dc0622_is.jpg", "is_org": false, "follower_count": 8, "badge": []}, {"is_followed": false, "avatar_url_template": "https://pic4.zhimg.com/v2-755589852329d806d46022ca5feb032b_{size}.jpg", "user_type": "people", "answer_count": 1, "is_following": false, "headline": "\u672a\u8ba4\u77e5\u5b69\u5b50", "url_token": "yao-bi-cheng-53", "id": "48652605a2290afd47cdbd61d64bd708", "articles_count": 0, "type": "people", "name": "\u4f0a\u4f0a\u6811", "url": "https://www.zhihu.com/people/48652605a2290afd47cdbd61d64bd708", "gender": -1, "vip_info": {"is_vip": false}, "is_advertiser": false, "avatar_url": "https://pic4.zhimg.com/v2-755589852329d806d46022ca5feb032b_is.jpg", "is_org": false, "follower_count": 4, "badge": []}, {"is_followed": false, "avatar_url_template": "https://pic1.zhimg.com/da8e974dc_{size}.jpg", "user_type": "people", "answer_count": 3, "is_following": false, "headline": "\u603b\u662f\u597d\u5947\u7684\u8001\u7537\u5b69", "url_token": "bei-ming-zhi-yu-12", "id": "89210039169ca74ba28a524a18ceae03", "articles_count": 0, "type": "people", "name": "\u5317\u51a5\u4e4b\u9c7c", "url": "https://www.zhihu.com/people/89210039169ca74ba28a524a18ceae03", "gender": -1, "vip_info": {"is_vip": false}, "is_advertiser": false, "avatar_url": "https://pic1.zhimg.com/da8e974dc_is.jpg", "is_org": false, "follower_count": 1, "badge": []}, {"is_followed": false, "avatar_url_template": "https://pic2.zhimg.com/0c858e1f54afa46240292a89e73debc9_{size}.jpg", "user_type": "people", "answer_count": 8, "is_following": false, "headline": "\u86e4\u86e4", "url_token": "kong-cheng-jiu-meng-19", "id": "fb8982e559f60cf5dbad3eeb7a0401a5", "articles_count": 0, "type": "people", "name": "\u7a7a\u57ce\u65e7\u68a6", "url": "https://www.zhihu.com/people/fb8982e559f60cf5dbad3eeb7a0401a5", "gender": 1, "vip_info": {"is_vip": false}, "is_advertiser": false, "avatar_url": "https://pic2.zhimg.com/0c858e1f54afa46240292a89e73debc9_is.jpg", "is_org": false, "follower_count": 1, "badge": []}, {"is_followed": false, "avatar_url_template": "https://pic2.zhimg.com/v2-086a29f80104cf4d674560e02f85a095_{size}.jpg", "user_type": "people", "answer_count": 534, "is_following": false, "headline": "\u4eba\u618e\u6068\u4e00\u6837\u4e8b\u7269\u7684\u65f6\u5019\uff0c\u5c31\u4f1a\u4e0d\u81ea\u89c9\u8ba4\u540c\u5b83\u7684\u5bf9\u7acb\u9762\u4e86\u3002", "url_token": "wang-yu-26-91-21", "id": "7708028cf18e7956575f2510d66f6211", "articles_count": 0, "type": "people", "name": "\u5929\u9645\u72c2\u9b54\u6293\u6839\u5b9d", "url": "https://www.zhihu.com/people/7708028cf18e7956575f2510d66f6211", "gender": 1, "vip_info": {"is_vip": false}, "is_advertiser": false, "avatar_url": "https://pic2.zhimg.com/v2-086a29f80104cf4d674560e02f85a095_is.jpg", "is_org": false, "follower_count": 1439, "badge": []}, {"is_followed": false, "avatar_url_template": "https://pic1.zhimg.com/da8e974dc_{size}.jpg", "user_type": "people", "answer_count": 6, "is_following": false, "headline": "", "url_token": "tudidj", "id": "edd7edb9ec074df6f84ba7b4102f0f95", "articles_count": 0, "type": "people", "name": "tudidj", "url": "https://www.zhihu.com/people/edd7edb9ec074df6f84ba7b4102f0f95", "gender": -1, "vip_info": {"is_vip": false}, "is_advertiser": false, "avatar_url": "https://pic1.zhimg.com/da8e974dc_is.jpg", "is_org": false, "follower_count": 0, "badge": []}, {"is_followed": false, "avatar_url_template": "https://pic1.zhimg.com/da8e974dc_{size}.jpg", "user_type": "people", "answer_count": 20, "is_following": false, "headline": "\u7537\u5973\u4ea4\u5f80\u54a8\u8be2\u5e08\uff0c\u5efa\u7b51\u5bb6", "url_token": "zhao-da-hai-13-59", "id": "bbd60de95e69a57047b68e8c8e9ca819", "articles_count": 0, "type": "people", "name": "\u5475\u5475\u5475\u5475\u5475\u5475", "url": "https://www.zhihu.com/people/bbd60de95e69a57047b68e8c8e9ca819", "gender": -1, "vip_info": {"is_vip": false}, "is_advertiser": false, "avatar_url": "https://pic1.zhimg.com/da8e974dc_is.jpg", "is_org": false, "follower_count": 2, "badge": []}, {"is_followed": false, "avatar_url_template": "https://pic2.zhimg.com/v2-4a5d4812fd02d3eacc93bdb9bfdd0cb5_{size}.jpg", "user_type": "people", "answer_count": 0, "is_following": false, "headline": "", "url_token": "ba-wo-de-xiao-xiong-huan-gei-wo-13", "id": "707d55ced0cf3df5ea51e58b6f2fadf7", "articles_count": 0, "type": "people", "name": "\u628a\u6211\u7684\u5c0f\u718a\u8fd8\u7ed9\u6211", "url": "https://www.zhihu.com/people/707d55ced0cf3df5ea51e58b6f2fadf7", "gender": -1, "vip_info": {"is_vip": false}, "is_advertiser": false, "avatar_url": "https://pic2.zhimg.com/v2-4a5d4812fd02d3eacc93bdb9bfdd0cb5_is.jpg", "is_org": false, "follower_count": 0, "badge": []}, {"is_followed": false, "avatar_url_template": "https://pic1.zhimg.com/v2-17d754e3be43af693920b556c94aa730_{size}.jpg", "user_type": "people", "answer_count": 16, "is_following": false, "headline": "\u5b66\u751f\uff0c\u7231\u6c34\u5f69\uff0c", "url_token": "cheng-zi-cheng-zi-75", "id": "6fa01f54c4b8059531c0511d8e2ff5fa", "articles_count": 2, "type": "people", "name": "\u4e00\u53ea\u5e05\u9e45", "url": "https://www.zhihu.com/people/6fa01f54c4b8059531c0511d8e2ff5fa", "gender": 0, "vip_info": {"is_vip": false}, "is_advertiser": false, "avatar_url": "https://pic1.zhimg.com/v2-17d754e3be43af693920b556c94aa730_is.jpg", "is_org": false, "follower_count": 2, "badge": []}, {"is_followed": false, "avatar_url_template": "https://pic1.zhimg.com/da8e974dc_{size}.jpg", "user_type": "people", "answer_count": 2, "is_following": false, "headline": "", "url_token": "neutrino-29", "id": "5bfb699f19a8dd6573fb5c7507118fa0", "articles_count": 0, "type": "people", "name": "Neutrino", "url": "https://www.zhihu.com/people/5bfb699f19a8dd6573fb5c7507118fa0", "gender": -1, "vip_info": {"is_vip": false}, "is_advertiser": false, "avatar_url": "https://pic1.zhimg.com/da8e974dc_is.jpg", "is_org": false, "follower_count": 2, "badge": []}, {"is_followed": false, "avatar_url_template": "https://pic2.zhimg.com/ead62d11f69d0e907aae1402d01c40f1_{size}.jpg", "user_type": "people", "answer_count": 4, "is_following": false, "headline": "", "url_token": "zhou-yi-54-77-34", "id": "34b90919b147aaa397f15444f3031535", "articles_count": 0, "type": "people", "name": "\u5468\u4e00", "url": "https://www.zhihu.com/people/34b90919b147aaa397f15444f3031535", "gender": 1, "vip_info": {"is_vip": false}, "is_advertiser": false, "avatar_url": "https://pic2.zhimg.com/ead62d11f69d0e907aae1402d01c40f1_is.jpg", "is_org": false, "follower_count": 1, "badge": []}, {"is_followed": false, "avatar_url_template": "https://pic3.zhimg.com/v2-b430586757d5715e61622dbf38767ff2_{size}.jpg", "user_type": "people", "answer_count": 0, "is_following": false, "headline": "\u624b\u673a", "url_token": "liu-xin-quan-27", "id": "ccf031d1d5f3b5abd6f68db5604cb699", "articles_count": 0, "type": "people", "name": "\u5468\u745c", "url": "https://www.zhihu.com/people/ccf031d1d5f3b5abd6f68db5604cb699", "gender": -1, "vip_info": {"is_vip": false}, "is_advertiser": false, "avatar_url": "https://pic3.zhimg.com/v2-b430586757d5715e61622dbf38767ff2_is.jpg", "is_org": false, "follower_count": 0, "badge": []}, {"is_followed": false, "avatar_url_template": "https://pic1.zhimg.com/da8e974dc_{size}.jpg", "user_type": "people", "answer_count": 0, "is_following": false, "headline": "", "url_token": "ma-hao-yu-87-94", "id": "24f9a4253f362403b43da765ebac39f3", "articles_count": 0, "type": "people", "name": "\u9a6c\u704f\u5c7f", "url": "https://www.zhihu.com/people/24f9a4253f362403b43da765ebac39f3", "gender": -1, "vip_info": {"is_vip": false}, "is_advertiser": false, "avatar_url": "https://pic1.zhimg.com/da8e974dc_is.jpg", "is_org": false, "follower_count": 0, "badge": []}, {"is_followed": false, "avatar_url_template": "https://pic2.zhimg.com/v2-5949a1c635cb1fd26b7b64f66c65c669_{size}.jpg", "user_type": "people", "answer_count": 28, "is_following": false, "headline": "", "url_token": "ning-ye-zi-43", "id": "477c42c5cfd2b540183897834c985923", "articles_count": 0, "type": "people", "name": "\u56de\u7518", "url": "https://www.zhihu.com/people/477c42c5cfd2b540183897834c985923", "gender": -1, "vip_info": {"is_vip": false}, "is_advertiser": false, "avatar_url": "https://pic2.zhimg.com/v2-5949a1c635cb1fd26b7b64f66c65c669_is.jpg", "is_org": false, "follower_count": 85, "badge": []}, {"is_followed": false, "avatar_url_template": "https://pic1.zhimg.com/v2-570bd99834e2d9cfe142bcd7238f3e98_{size}.jpg", "user_type": "people", "answer_count": 0, "is_following": false, "headline": "", "url_token": "wai-du", "id": "560f41425812d30abd7c8a32bcd92c4d", "articles_count": 0, "type": "people", "name": "\u6b6a\u90fd", "url": "https://www.zhihu.com/people/560f41425812d30abd7c8a32bcd92c4d", "gender": -1, "vip_info": {"is_vip": false}, "is_advertiser": false, "avatar_url": "https://pic1.zhimg.com/v2-570bd99834e2d9cfe142bcd7238f3e98_is.jpg", "is_org": false, "follower_count": 0, "badge": []}, {"is_followed": false, "avatar_url_template": "https://pic1.zhimg.com/da8e974dc_{size}.jpg", "user_type": "people", "answer_count": 8, "is_following": false, "headline": "", "url_token": "zhu-ge-dan-7", "id": "9c3369736acc1c6ed4c17bf373f7e792", "articles_count": 0, "type": "people", "name": "\u8bf8\u845b\u8bde", "url": "https://www.zhihu.com/people/9c3369736acc1c6ed4c17bf373f7e792", "gender": -1, "vip_info": {"is_vip": false}, "is_advertiser": false, "avatar_url": "https://pic1.zhimg.com/da8e974dc_is.jpg", "is_org": false, "follower_count": 0, "badge": []}]}