{"paging": {"is_end": false, "totals": 30872, "previous": "https://www.zhihu.com/members/shi-kong-23-21/followers?per_page=20&include=data%5B%2A%5D.answer_count%2Carticles_count%2Cfollower_count%2Cis_followed%2Cis_following%2Cbadge%5B%3F%28type%3Dbest_answerer%29%5D.topics&limit=20&offset=19180", "is_start": false, "next": "https://www.zhihu.com/members/shi-kong-23-21/followers?per_page=20&include=data%5B%2A%5D.answer_count%2Carticles_count%2Cfollower_count%2Cis_followed%2Cis_following%2Cbadge%5B%3F%28type%3Dbest_answerer%29%5D.topics&limit=20&offset=19220"}, "data": [{"is_followed": false, "avatar_url_template": "https://pic1.zhimg.com/da8e974dc_{size}.jpg", "user_type": "people", "answer_count": 0, "is_following": false, "headline": "", "url_token": "jerryliu-9", "id": "4067d7cf4efdb9e48119aeb567219489", "articles_count": 0, "type": "people", "name": "Jerry\u5218", "url": "https://www.zhihu.com/people/4067d7cf4efdb9e48119aeb567219489", "gender": -1, "vip_info": {"is_vip": false}, "is_advertiser": false, "avatar_url": "https://pic1.zhimg.com/da8e974dc_is.jpg", "is_org": false, "follower_count": 0, "badge": []}, {"is_followed": false, "avatar_url_template": "https://pic3.zhimg.com/v2-c05ebecc76f3afb0b3738cd522c257a6_{size}.jpg", "user_type": "people", "answer_count": 0, "is_following": false, "headline": "", "url_token": "mzt-21-82", "id": "54424eb62db83c9b98d363a6d1a60948", "articles_count": 0, "type": "people", "name": "speechless", "url": "https://www.zhihu.com/people/54424eb62db83c9b98d363a6d1a60948", "gender": 1, "vip_info": {"is_vip": false}, "is_advertiser": false, "avatar_url": "https://pic3.zhimg.com/v2-c05ebecc76f3afb0b3738cd522c257a6_is.jpg", "is_org": false, "follower_count": 0, "badge": []}, {"is_followed": false, "avatar_url_template": "https://pic1.zhimg.com/da8e974dc_{size}.jpg", "user_type": "people", "answer_count": 0, "is_following": false, "headline": "", "url_token": "la-la-lou-68", "id": "2655a56d8068d2ce5d33f61ac4707662", "articles_count": 0, "type": "people", "name": "\u62c9\u62c9\u697c", "url": "https://www.zhihu.com/people/2655a56d8068d2ce5d33f61ac4707662", "gender": -1, "vip_info": {"is_vip": false}, "is_advertiser": false, "avatar_url": "https://pic1.zhimg.com/da8e974dc_is.jpg", "is_org": false, "follower_count": 0, "badge": []}, {"is_followed": false, "avatar_url_template": "https://pic2.zhimg.com/v2-5af91094ac2be736dae3bbc4a2f08f9d_{size}.jpg", "user_type": "people", "answer_count": 3, "is_following": false, "headline": "", "url_token": "hao-yue-dang-kong-54-7", "id": "b23beacfa744c680403c565a8694e542", "articles_count": 0, "type": "people", "name": "\u7693\u6708\u5f53\u7a7a", "url": "https://www.zhihu.com/people/b23beacfa744c680403c565a8694e542", "gender": -1, "vip_info": {"is_vip": false}, "is_advertiser": false, "avatar_url": "https://pic2.zhimg.com/v2-5af91094ac2be736dae3bbc4a2f08f9d_is.jpg", "is_org": false, "follower_count": 0, "badge": []}, {"is_followed": false, "avatar_url_template": "https://pic1.zhimg.com/da8e974dc_{size}.jpg", "user_type": "people", "answer_count": 0, "is_following": false, "headline": "", "url_token": "a-ya-a-ya-shi-yan-yan-a", "id": "ccaacdb86e90986181cfb8912fb39c04", "articles_count": 0, "type": "people", "name": "\u554a\u5440\u554a\u5440\u662f\u598d\u598d\u554a", "url": "https://www.zhihu.com/people/ccaacdb86e90986181cfb8912fb39c04", "gender": -1, "vip_info": {"is_vip": false}, "is_advertiser": false, "avatar_url": "https://pic1.zhimg.com/da8e974dc_is.jpg", "is_org": false, "follower_count": 0, "badge": []}, {"is_followed": false, "avatar_url_template": "https://pic1.zhimg.com/da8e974dc_{size}.jpg", "user_type": "people", "answer_count": 2, "is_following": false, "headline": "\u81f4\u529b\u4e8e\u7406\u5de5\u7c7b\u7684\u5984\u60f3\u8131\u5355\u7684\u5927\u5b66\u50e7", "url_token": "lao-ge-94-20", "id": "fbb05799d16dad485390fcc0c1c4683d", "articles_count": 0, "type": "people", "name": "\u8001\u54e5", "url": "https://www.zhihu.com/people/fbb05799d16dad485390fcc0c1c4683d", "gender": -1, "vip_info": {"is_vip": false}, "is_advertiser": false, "avatar_url": "https://pic1.zhimg.com/da8e974dc_is.jpg", "is_org": false, "follower_count": 2, "badge": []}, {"is_followed": false, "avatar_url_template": "https://pic1.zhimg.com/v2-81efda3e6e3413a38b644bcfc5020fb8_{size}.jpg", "user_type": "people", "answer_count": 0, "is_following": false, "headline": "\u5b66\u751f", "url_token": "alcohol-45-48", "id": "17884691acc9050de36c82544e374440", "articles_count": 0, "type": "people", "name": "BaaaoSJ", "url": "https://www.zhihu.com/people/17884691acc9050de36c82544e374440", "gender": 1, "vip_info": {"is_vip": false}, "is_advertiser": false, "avatar_url": "https://pic1.zhimg.com/v2-81efda3e6e3413a38b644bcfc5020fb8_is.jpg", "is_org": false, "follower_count": 0, "badge": []}, {"is_followed": false, "avatar_url_template": "https://pic2.zhimg.com/v2-0f04875985b8f04bd53849b954724eb1_{size}.jpg", "user_type": "people", "answer_count": 8, "is_following": false, "headline": "\u4e25\u4e8e\u5f8b\u5df1\uff0c\u5bbd\u4ee5\u5f85\u4eba", "url_token": "xiao-ai-26-86-68", "id": "20fa8a68f32385a144e9f0ff5c5900d2", "articles_count": 0, "type": "people", "name": "\u5c0f\u7231", "url": "https://www.zhihu.com/people/20fa8a68f32385a144e9f0ff5c5900d2", "gender": 0, "vip_info": {"is_vip": false}, "is_advertiser": false, "avatar_url": "https://pic2.zhimg.com/v2-0f04875985b8f04bd53849b954724eb1_is.jpg", "is_org": false, "follower_count": 47, "badge": []}, {"is_followed": false, "avatar_url_template": "https://pic3.zhimg.com/v2-f96195a8e0010719c23bdebda988d29a_{size}.jpg", "user_type": "people", "answer_count": 0, "is_following": false, "headline": "ARASHI\u72c2\u70ed\u4e2d \u2764   ", "url_token": "11037-77", "id": "bbd39d97536de64ac679adc834c5a206", "articles_count": 0, "type": "people", "name": "\u786b\u9178\u9178\u9178\u9178", "url": "https://www.zhihu.com/people/bbd39d97536de64ac679adc834c5a206", "gender": -1, "vip_info": {"is_vip": false}, "is_advertiser": false, "avatar_url": "https://pic3.zhimg.com/v2-f96195a8e0010719c23bdebda988d29a_is.jpg", "is_org": false, "follower_count": 0, "badge": []}, {"is_followed": false, "avatar_url_template": "https://pic4.zhimg.com/v2-e936df1472c2f65d4aa7e487c6aa979f_{size}.jpg", "user_type": "people", "answer_count": 0, "is_following": false, "headline": "", "url_token": "superlin-5", "id": "dcc432e868c618e52c5aed96cbb9e336", "articles_count": 0, "type": "people", "name": "super\u7433", "url": "https://www.zhihu.com/people/dcc432e868c618e52c5aed96cbb9e336", "gender": -1, "vip_info": {"is_vip": false}, "is_advertiser": false, "avatar_url": "https://pic4.zhimg.com/v2-e936df1472c2f65d4aa7e487c6aa979f_is.jpg", "is_org": false, "follower_count": 1, "badge": []}, {"is_followed": false, "avatar_url_template": "https://pic3.zhimg.com/v2-b48bab5b67ee90cd9011c0bafe628fba_{size}.jpg", "user_type": "people", "answer_count": 7, "is_following": false, "headline": "\u8db3\u7403 \u7687\u9a6c C\u7f57 \u5468\u6770\u4f26 \u6797\u4fca\u6770", "url_token": "xiao-huang-61-62", "id": "2acb13f4198bf42dda890b8005bc9229", "articles_count": 0, "type": "people", "name": "\u5c0f\u9ec4", "url": "https://www.zhihu.com/people/2acb13f4198bf42dda890b8005bc9229", "gender": -1, "vip_info": {"is_vip": false}, "is_advertiser": false, "avatar_url": "https://pic3.zhimg.com/v2-b48bab5b67ee90cd9011c0bafe628fba_is.jpg", "is_org": false, "follower_count": 13, "badge": []}, {"is_followed": false, "avatar_url_template": "https://pic1.zhimg.com/da8e974dc_{size}.jpg", "user_type": "people", "answer_count": 0, "is_following": false, "headline": "\u5b66\u4e60\u4e2d", "url_token": "xiao-ke-xue-sheng-53", "id": "956540d15c37f0785cebabd908fb896a", "articles_count": 0, "type": "people", "name": "\u5c0f\u79d1\u5b66\u751f", "url": "https://www.zhihu.com/people/956540d15c37f0785cebabd908fb896a", "gender": -1, "vip_info": {"is_vip": false}, "is_advertiser": false, "avatar_url": "https://pic1.zhimg.com/da8e974dc_is.jpg", "is_org": false, "follower_count": 0, "badge": []}, {"is_followed": false, "avatar_url_template": "https://pic1.zhimg.com/da8e974dc_{size}.jpg", "user_type": "people", "answer_count": 0, "is_following": false, "headline": "\u5b66\u751f", "url_token": "shiren-58", "id": "2a588c63a2c5df775644452173f37e3c", "articles_count": 0, "type": "people", "name": "shiren", "url": "https://www.zhihu.com/people/2a588c63a2c5df775644452173f37e3c", "gender": -1, "vip_info": {"is_vip": false}, "is_advertiser": false, "avatar_url": "https://pic1.zhimg.com/da8e974dc_is.jpg", "is_org": false, "follower_count": 0, "badge": []}, {"is_followed": false, "avatar_url_template": "https://pic1.zhimg.com/da8e974dc_{size}.jpg", "user_type": "people", "answer_count": 0, "is_following": false, "headline": "", "url_token": "fei-ji-da-dui", "id": "ebada85947540fe14bd0c276081e14cb", "articles_count": 0, "type": "people", "name": "\u98de\u673a\u5927\u961f", "url": "https://www.zhihu.com/people/ebada85947540fe14bd0c276081e14cb", "gender": -1, "vip_info": {"is_vip": false}, "is_advertiser": false, "avatar_url": "https://pic1.zhimg.com/da8e974dc_is.jpg", "is_org": false, "follower_count": 0, "badge": []}, {"is_followed": false, "avatar_url_template": "https://pic1.zhimg.com/v2-254f307dc855133d889fe716418d0b50_{size}.jpg", "user_type": "people", "answer_count": 0, "is_following": false, "headline": "\u4f1a\u8ba1\u5728\u8bfb\uff0c\u8d44\u6df1\u5b85\u7537\uff0c\u6e38\u620f\u8fbe\u4eba", "url_token": "yimi-er-de-pan-duo-la", "id": "37ac461e87bf13880baca0412c8d0dbb", "articles_count": 0, "type": "people", "name": "\u4e00\u7c73\u4e8c\u7684\u6f58\u591a\u62c9", "url": "https://www.zhihu.com/people/37ac461e87bf13880baca0412c8d0dbb", "gender": -1, "vip_info": {"is_vip": false}, "is_advertiser": false, "avatar_url": "https://pic1.zhimg.com/v2-254f307dc855133d889fe716418d0b50_is.jpg", "is_org": false, "follower_count": 0, "badge": []}, {"is_followed": false, "avatar_url_template": "https://pic1.zhimg.com/v2-0524d2d9c1d7a8f1e0c056870e7e5ed4_{size}.jpg", "user_type": "people", "answer_count": 15, "is_following": false, "headline": "\u604b\u7231  \u7269\u7406", "url_token": "mok-zi-59", "id": "252d84e9991b517ceab5f5fcd1ed527f", "articles_count": 0, "type": "people", "name": "\u6076\u610f", "url": "https://www.zhihu.com/people/252d84e9991b517ceab5f5fcd1ed527f", "gender": 1, "vip_info": {"is_vip": false}, "is_advertiser": false, "avatar_url": "https://pic1.zhimg.com/v2-0524d2d9c1d7a8f1e0c056870e7e5ed4_is.jpg", "is_org": false, "follower_count": 2, "badge": []}, {"is_followed": false, "avatar_url_template": "https://pic1.zhimg.com/da8e974dc_{size}.jpg", "user_type": "people", "answer_count": 0, "is_following": false, "headline": "", "url_token": "000001-67", "id": "80a224027ce5afd2856d06385597b5ae", "articles_count": 0, "type": "people", "name": "000001", "url": "https://www.zhihu.com/people/80a224027ce5afd2856d06385597b5ae", "gender": -1, "vip_info": {"is_vip": false}, "is_advertiser": false, "avatar_url": "https://pic1.zhimg.com/da8e974dc_is.jpg", "is_org": false, "follower_count": 0, "badge": []}, {"is_followed": false, "avatar_url_template": "https://pic4.zhimg.com/630e940559b0b51436ffa8afe05e1183_{size}.jpg", "user_type": "people", "answer_count": 0, "is_following": false, "headline": "", "url_token": "tar-lok-61", "id": "dc23eea2d28127845b24cd3c2d43fbe6", "articles_count": 0, "type": "people", "name": "tar lok", "url": "https://www.zhihu.com/people/dc23eea2d28127845b24cd3c2d43fbe6", "gender": 1, "vip_info": {"is_vip": false}, "is_advertiser": false, "avatar_url": "https://pic4.zhimg.com/630e940559b0b51436ffa8afe05e1183_is.jpg", "is_org": false, "follower_count": 1, "badge": []}, {"is_followed": false, "avatar_url_template": "https://pic3.zhimg.com/v2-bb06584e84ebf91a91a8a3593acf41c2_{size}.jpg", "user_type": "people", "answer_count": 2, "is_following": false, "headline": "\u73b0\u5b9e\u603b\u4f1a\u6247\u4eba\u8033\u5149\uff0c\u53ea\u6709\u8fd9\u70b9\u4ece\u672a\u8ba9\u4eba\u5931\u671b", "url_token": "name520", "id": "d432e086fc2f72baa307b485a842f8d5", "articles_count": 0, "type": "people", "name": "name", "url": "https://www.zhihu.com/people/d432e086fc2f72baa307b485a842f8d5", "gender": -1, "vip_info": {"is_vip": false}, "is_advertiser": false, "avatar_url": "https://pic3.zhimg.com/v2-bb06584e84ebf91a91a8a3593acf41c2_is.jpg", "is_org": false, "follower_count": 1, "badge": []}, {"is_followed": false, "avatar_url_template": "https://pic2.zhimg.com/v2-26c5e57f64dc0e5bc37f003ef393e389_{size}.jpg", "user_type": "people", "answer_count": 1, "is_following": false, "headline": "", "url_token": "ma-rong-18-2", "id": "d9ab2018e6c801badf19052d8d3e8c6a", "articles_count": 0, "type": "people", "name": "\u6b7b\u5566\u6b7b\u5566", "url": "https://www.zhihu.com/people/d9ab2018e6c801badf19052d8d3e8c6a", "gender": 0, "vip_info": {"is_vip": false}, "is_advertiser": false, "avatar_url": "https://pic2.zhimg.com/v2-26c5e57f64dc0e5bc37f003ef393e389_is.jpg", "is_org": false, "follower_count": 57, "badge": []}]}