{"paging": {"is_end": false, "totals": 30907, "previous": "https://www.zhihu.com/members/shi-kong-23-21/followers?per_page=20&include=data%5B%2A%5D.answer_count%2Carticles_count%2Cfollower_count%2Cis_followed%2Cis_following%2Cbadge%5B%3F%28type%3Dbest_answerer%29%5D.topics&limit=20&offset=24160", "is_start": false, "next": "https://www.zhihu.com/members/shi-kong-23-21/followers?per_page=20&include=data%5B%2A%5D.answer_count%2Carticles_count%2Cfollower_count%2Cis_followed%2Cis_following%2Cbadge%5B%3F%28type%3Dbest_answerer%29%5D.topics&limit=20&offset=24200"}, "data": [{"is_followed": false, "avatar_url_template": "https://pic2.zhimg.com/v2-9ffcffdd7589d42ed8455ae4b1b996d9_{size}.jpg", "user_type": "people", "answer_count": 44, "is_following": false, "url_token": "he-zhi-kuang", "id": "e26f360d8350c0a9a6ea202fc9b6b3b4", "articles_count": 0, "name": "\u4f55\u81f3\u72c2", "is_advertiser": false, "url": "https://www.zhihu.com/people/e26f360d8350c0a9a6ea202fc9b6b3b4", "type": "people", "vip_info": {"is_vip": false}, "headline": "\u4e00\u4e2a\u666e\u901a\u7684\u8bd7\u8bcd\u6587\u5b66\u7231\u597d\u8005\uff0c\u4e1a\u4f59\u7231\u597d\u662f\u603c\u4eba\u3002", "avatar_url": "https://pic2.zhimg.com/v2-9ffcffdd7589d42ed8455ae4b1b996d9_is.jpg", "is_org": false, "gender": -1, "follower_count": 16, "badge": []}, {"is_followed": false, "avatar_url_template": "https://pic2.zhimg.com/v2-1ef088b96f3685230df761f81a89ec0d_{size}.jpg", "user_type": "people", "answer_count": 0, "is_following": false, "url_token": "ying-huo-61-28", "id": "bb8ec35ea267f55c354c4f37ed3d134b", "articles_count": 0, "name": "\u6c99\u96d5\u7f51\u53cb\u8424\u706b\u706b", "is_advertiser": false, "url": "https://www.zhihu.com/people/bb8ec35ea267f55c354c4f37ed3d134b", "type": "people", "vip_info": {"is_vip": false}, "headline": "\u5feb\u843d\u80a5\u5b85 \u6c99\u96d5\u7f51\u53cb", "avatar_url": "https://pic2.zhimg.com/v2-1ef088b96f3685230df761f81a89ec0d_is.jpg", "is_org": false, "gender": 0, "follower_count": 1, "badge": []}, {"is_followed": false, "avatar_url_template": "https://pic1.zhimg.com/da8e974dc_{size}.jpg", "user_type": "people", "answer_count": 0, "is_following": false, "url_token": "tu-yang-24-72", "id": "924ff0c6ca423bd07ea1778559325995", "articles_count": 0, "name": "\u5c60\u6837", "is_advertiser": false, "url": "https://www.zhihu.com/people/924ff0c6ca423bd07ea1778559325995", "type": "people", "vip_info": {"is_vip": false}, "headline": "QQ\u7cd6\u8638\u82a5\u672b", "avatar_url": "https://pic1.zhimg.com/da8e974dc_is.jpg", "is_org": false, "gender": 1, "follower_count": 0, "badge": []}, {"is_followed": false, "avatar_url_template": "https://pic3.zhimg.com/v2-bef3e14c7356c02146761c9c93341e42_{size}.jpg", "user_type": "people", "answer_count": 0, "is_following": false, "url_token": "qiu-hong-tao-96-68", "id": "81de2b9dc173f08fbb89713efdaba70d", "articles_count": 0, "name": "\u90b1\u6cd3\u97ec", "is_advertiser": false, "url": "https://www.zhihu.com/people/81de2b9dc173f08fbb89713efdaba70d", "type": "people", "vip_info": {"is_vip": false}, "headline": "\u5141\u6267\u53a5\u4e2d", "avatar_url": "https://pic3.zhimg.com/v2-bef3e14c7356c02146761c9c93341e42_is.jpg", "is_org": false, "gender": 1, "follower_count": 15, "badge": []}, {"is_followed": false, "avatar_url_template": "https://pic3.zhimg.com/v2-f1ec0ea3301e3da0fc58e910d3bd6f7e_{size}.jpg", "user_type": "people", "answer_count": 1, "is_following": false, "url_token": "ke-ai-de-zong-zong", "id": "3f8ebf96b65cf2bd2ef3a6e284cbcdb9", "articles_count": 0, "name": "BZKL", "is_advertiser": false, "url": "https://www.zhihu.com/people/3f8ebf96b65cf2bd2ef3a6e284cbcdb9", "type": "people", "vip_info": {"is_vip": false}, "headline": "\u53ef\u4e50\u7231\u597d\u8005", "avatar_url": "https://pic3.zhimg.com/v2-f1ec0ea3301e3da0fc58e910d3bd6f7e_is.jpg", "is_org": false, "gender": 0, "follower_count": 0, "badge": []}, {"is_followed": false, "avatar_url_template": "https://pic3.zhimg.com/v2-fbfcf11e90b2e9a7e2845993ff68e6a6_{size}.jpg", "user_type": "people", "answer_count": 6, "is_following": false, "url_token": "bai-yan-90-84", "id": "44d383d1add0d1cbef46f3826220adc2", "articles_count": 0, "name": "\u767d\u8a00", "is_advertiser": false, "url": "https://www.zhihu.com/people/44d383d1add0d1cbef46f3826220adc2", "type": "people", "vip_info": {"is_vip": false}, "headline": "\u5b66\u751f", "avatar_url": "https://pic3.zhimg.com/v2-fbfcf11e90b2e9a7e2845993ff68e6a6_is.jpg", "is_org": false, "gender": -1, "follower_count": 3, "badge": []}, {"is_followed": false, "avatar_url_template": "https://pic4.zhimg.com/v2-e93c07cb133aafe4ff8a72675e6ebe3f_{size}.jpg", "user_type": "people", "answer_count": 25, "is_following": false, "url_token": "zgrxtf", "id": "565d184084217be610f3b30f9c8dece6", "articles_count": 0, "name": "\u4ec5\u6b64\u800c\u5df2", "is_advertiser": false, "url": "https://www.zhihu.com/people/565d184084217be610f3b30f9c8dece6", "type": "people", "vip_info": {"is_vip": false}, "headline": "\u5b66\u751f", "avatar_url": "https://pic4.zhimg.com/v2-e93c07cb133aafe4ff8a72675e6ebe3f_is.jpg", "is_org": false, "gender": -1, "follower_count": 1, "badge": []}, {"is_followed": false, "avatar_url_template": "https://pic1.zhimg.com/v2-49d8e18304bdae216a23601370792b14_{size}.jpg", "user_type": "people", "answer_count": 38, "is_following": false, "url_token": "liu-jing-wen-35-37", "id": "aec77256aa502ee8b79577ce074d8052", "articles_count": 0, "name": "\u674f\u4ec1", "is_advertiser": false, "url": "https://www.zhihu.com/people/aec77256aa502ee8b79577ce074d8052", "type": "people", "vip_info": {"is_vip": false}, "headline": "Minecraft\u5927\u65d7\u6c38\u4e0d\u5012", "avatar_url": "https://pic1.zhimg.com/v2-49d8e18304bdae216a23601370792b14_is.jpg", "is_org": false, "gender": -1, "follower_count": 3, "badge": []}, {"is_followed": false, "avatar_url_template": "https://pic3.zhimg.com/v2-d63575fb27df8025c0f439da0d4decae_{size}.jpg", "user_type": "people", "answer_count": 0, "is_following": false, "url_token": "moziling", "id": "57110257b22cf12add6ac54cf8a93d8c", "articles_count": 0, "name": "MoZiLing", "is_advertiser": false, "url": "https://www.zhihu.com/people/57110257b22cf12add6ac54cf8a93d8c", "type": "people", "vip_info": {"is_vip": false}, "headline": "MoYou", "avatar_url": "https://pic3.zhimg.com/v2-d63575fb27df8025c0f439da0d4decae_is.jpg", "is_org": false, "gender": -1, "follower_count": 0, "badge": []}, {"is_followed": false, "avatar_url_template": "https://pic4.zhimg.com/v2-209e57ba598bc1569c7f04552270e313_{size}.jpg", "user_type": "people", "answer_count": 0, "is_following": false, "url_token": "xi-huan-ti-an-de-xi", "id": "a727c586970fb2bc5bcf3cede137de25", "articles_count": 0, "name": "\u559c\u6b22\u7cd6\u7684\u563b", "is_advertiser": false, "url": "https://www.zhihu.com/people/a727c586970fb2bc5bcf3cede137de25", "type": "people", "vip_info": {"is_vip": false}, "headline": "\u841d\u8389\u7814\u7a76\u6240\u6240\u957f", "avatar_url": "https://pic4.zhimg.com/v2-209e57ba598bc1569c7f04552270e313_is.jpg", "is_org": false, "gender": -1, "follower_count": 0, "badge": []}, {"is_followed": false, "avatar_url_template": "https://pic1.zhimg.com/v2-5496aba7a71ea9d15500ec8e52eec91c_{size}.jpg", "user_type": "people", "answer_count": 1, "is_following": false, "url_token": "nayoki", "id": "2910e26d9b5b36ccd42f21032faaf55b", "articles_count": 0, "name": "Nayoki", "is_advertiser": false, "url": "https://www.zhihu.com/people/2910e26d9b5b36ccd42f21032faaf55b", "type": "people", "vip_info": {"is_vip": false}, "headline": "\u6587\u6c13\uff0c\u7687\u5bb6\u7406\u5de5\u5b66\u9662\u5728\u8bfb", "avatar_url": "https://pic1.zhimg.com/v2-5496aba7a71ea9d15500ec8e52eec91c_is.jpg", "is_org": false, "gender": -1, "follower_count": 0, "badge": []}, {"is_followed": false, "avatar_url_template": "https://pic3.zhimg.com/v2-4af80bff9dc786666636cc11f554dfa2_{size}.jpg", "user_type": "people", "answer_count": 4, "is_following": false, "url_token": "liu-xu-36-38", "id": "e66bcc53809e4ddd422c1c6b27544c96", "articles_count": 0, "name": "\u9cb8\u843d", "is_advertiser": false, "url": "https://www.zhihu.com/people/e66bcc53809e4ddd422c1c6b27544c96", "type": "people", "vip_info": {"is_vip": false}, "headline": "", "avatar_url": "https://pic3.zhimg.com/v2-4af80bff9dc786666636cc11f554dfa2_is.jpg", "is_org": false, "gender": 1, "follower_count": 4, "badge": []}, {"is_followed": false, "avatar_url_template": "https://pic1.zhimg.com/da8e974dc_{size}.jpg", "user_type": "people", "answer_count": 0, "is_following": false, "url_token": "gong-zhu-qian-59", "id": "6b0bbbe8483b00e1c2668507093ee03d", "articles_count": 0, "name": "\u516c\u4e3b\u9a9e", "is_advertiser": false, "url": "https://www.zhihu.com/people/6b0bbbe8483b00e1c2668507093ee03d", "type": "people", "vip_info": {"is_vip": false}, "headline": "", "avatar_url": "https://pic1.zhimg.com/da8e974dc_is.jpg", "is_org": false, "gender": -1, "follower_count": 0, "badge": []}, {"is_followed": false, "avatar_url_template": "https://pic1.zhimg.com/da8e974dc_{size}.jpg", "user_type": "people", "answer_count": 0, "is_following": false, "url_token": "yi-hai-hang-zhou", "id": "67623d0c75f683a13381b42a150e11aa", "articles_count": 0, "name": "\u827a\u6d77\u822a\u821f", "is_advertiser": false, "url": "https://www.zhihu.com/people/67623d0c75f683a13381b42a150e11aa", "type": "people", "vip_info": {"is_vip": false}, "headline": "\u5927\u5b66\u840c\u65b0", "avatar_url": "https://pic1.zhimg.com/da8e974dc_is.jpg", "is_org": false, "gender": -1, "follower_count": 0, "badge": []}, {"is_followed": false, "avatar_url_template": "https://pic4.zhimg.com/v2-3aff659d55b5aef020e5b8d2e40ad8cb_{size}.jpg", "user_type": "people", "answer_count": 6, "is_following": false, "url_token": "lin-ke-xin-69", "id": "b479c8ba3ce6d6ae5f4d546123e3df76", "articles_count": 0, "name": "\u5c0f\u5c0f\u5c0f\u53ef\u946b", "is_advertiser": false, "url": "https://www.zhihu.com/people/b479c8ba3ce6d6ae5f4d546123e3df76", "type": "people", "vip_info": {"is_vip": false}, "headline": "\u7a7a\u60f3\u5bb6", "avatar_url": "https://pic4.zhimg.com/v2-3aff659d55b5aef020e5b8d2e40ad8cb_is.jpg", "is_org": false, "gender": 0, "follower_count": 2, "badge": []}, {"is_followed": false, "avatar_url_template": "https://pic1.zhimg.com/da8e974dc_{size}.jpg", "user_type": "people", "answer_count": 0, "is_following": false, "url_token": "yu-feng-68-60", "id": "366e8bd97f782136e4bd0d0b6cfe2cab", "articles_count": 0, "name": "\u4e8e\u4e16\u5cf0", "is_advertiser": false, "url": "https://www.zhihu.com/people/366e8bd97f782136e4bd0d0b6cfe2cab", "type": "people", "vip_info": {"is_vip": false}, "headline": "", "avatar_url": "https://pic1.zhimg.com/da8e974dc_is.jpg", "is_org": false, "gender": -1, "follower_count": 1, "badge": []}, {"is_followed": false, "avatar_url_template": "https://pic4.zhimg.com/1ae147a51633be76c9a3da13bcdb0073_{size}.jpg", "user_type": "people", "answer_count": 1, "is_following": false, "url_token": "jiao-chun-49", "id": "f11048170895554b2208d9cb569cd554", "articles_count": 0, "name": "\u89d2\u6df3", "is_advertiser": false, "url": "https://www.zhihu.com/people/f11048170895554b2208d9cb569cd554", "type": "people", "vip_info": {"is_vip": false}, "headline": "\u5b66\u751f", "avatar_url": "https://pic4.zhimg.com/1ae147a51633be76c9a3da13bcdb0073_is.jpg", "is_org": false, "gender": -1, "follower_count": 0, "badge": []}, {"is_followed": false, "avatar_url_template": "https://pic1.zhimg.com/da8e974dc_{size}.jpg", "user_type": "people", "answer_count": 0, "is_following": false, "url_token": "qing-chun-zheng-wei-rui", "id": "3f8f43047357fbe29a3915cc1975de40", "articles_count": 0, "name": "\u9752\u6625\u6b63\u8473\u8564", "is_advertiser": false, "url": "https://www.zhihu.com/people/3f8f43047357fbe29a3915cc1975de40", "type": "people", "vip_info": {"is_vip": false}, "headline": "", "avatar_url": "https://pic1.zhimg.com/da8e974dc_is.jpg", "is_org": false, "gender": -1, "follower_count": 1, "badge": []}, {"is_followed": false, "avatar_url_template": "https://pic1.zhimg.com/da8e974dc_{size}.jpg", "user_type": "people", "answer_count": 4, "is_following": false, "url_token": "lin-ze-shen-37", "id": "15f0a6325a2bae795c32fc36c6e9cf6e", "articles_count": 0, "name": "\u6298\u6728\u5949\u592a\u90ce", "is_advertiser": false, "url": "https://www.zhihu.com/people/15f0a6325a2bae795c32fc36c6e9cf6e", "type": "people", "vip_info": {"is_vip": false}, "headline": "\u521d\u4e09\u5b66\u751f", "avatar_url": "https://pic1.zhimg.com/da8e974dc_is.jpg", "is_org": false, "gender": 1, "follower_count": 11, "badge": []}, {"is_followed": false, "avatar_url_template": "https://pic1.zhimg.com/da8e974dc_{size}.jpg", "user_type": "people", "answer_count": 0, "is_following": false, "url_token": "he-you-bing-9", "id": "101f7138c9d318fb67c17c308d491513", "articles_count": 0, "name": "\u9e64\u6709\u75c5", "is_advertiser": false, "url": "https://www.zhihu.com/people/101f7138c9d318fb67c17c308d491513", "type": "people", "vip_info": {"is_vip": false}, "headline": "", "avatar_url": "https://pic1.zhimg.com/da8e974dc_is.jpg", "is_org": false, "gender": -1, "follower_count": 0, "badge": []}]}