{"paging": {"is_end": false, "totals": 30836, "previous": "https://www.zhihu.com/members/shi-kong-23-21/followers?per_page=20&include=data%5B%2A%5D.answer_count%2Carticles_count%2Cfollower_count%2Cis_followed%2Cis_following%2Cbadge%5B%3F%28type%3Dbest_answerer%29%5D.topics&limit=20&offset=6800", "is_start": false, "next": "https://www.zhihu.com/members/shi-kong-23-21/followers?per_page=20&include=data%5B%2A%5D.answer_count%2Carticles_count%2Cfollower_count%2Cis_followed%2Cis_following%2Cbadge%5B%3F%28type%3Dbest_answerer%29%5D.topics&limit=20&offset=6840"}, "data": [{"is_followed": false, "avatar_url_template": "https://pic3.zhimg.com/v2-37ef1749448a5bbe5e53e532b30018ae_{size}.jpg", "user_type": "people", "answer_count": 3, "is_following": false, "url_token": "zhang-dong-jie-58", "id": "e1c3091a4f782e6631225ea90d11ed7b", "articles_count": 0, "name": "\u77f3\u6728\u5927\u7559", "is_advertiser": false, "url": "https://www.zhihu.com/people/e1c3091a4f782e6631225ea90d11ed7b", "type": "people", "vip_info": {"is_vip": false}, "headline": "", "avatar_url": "https://pic3.zhimg.com/v2-37ef1749448a5bbe5e53e532b30018ae_is.jpg", "is_org": false, "gender": 1, "follower_count": 0, "badge": []}, {"is_followed": false, "avatar_url_template": "https://pic4.zhimg.com/v2-9756bbb157f49888b9e98998336a339f_{size}.jpg", "user_type": "people", "answer_count": 18, "is_following": false, "url_token": "li-long-xin-67", "id": "7943f10d7b4e8087fd37531fdbcb5786", "articles_count": 0, "name": "\u51cc\u5c18", "is_advertiser": false, "url": "https://www.zhihu.com/people/7943f10d7b4e8087fd37531fdbcb5786", "type": "people", "vip_info": {"is_vip": false}, "headline": "Parsifal", "avatar_url": "https://pic4.zhimg.com/v2-9756bbb157f49888b9e98998336a339f_is.jpg", "is_org": false, "gender": 1, "follower_count": 36, "badge": []}, {"is_followed": false, "avatar_url_template": "https://pic1.zhimg.com/da8e974dc_{size}.jpg", "user_type": "people", "answer_count": 0, "is_following": false, "url_token": "yi-ge-la-ji-de-shu-xue-mi", "id": "d4ab1c8122ebf0585433580b5a2e29f3", "articles_count": 0, "name": "\u4e00\u4e2a\u8fa3\u9e21\u7684\u6570\u5b66\u8ff7", "is_advertiser": false, "url": "https://www.zhihu.com/people/d4ab1c8122ebf0585433580b5a2e29f3", "type": "people", "vip_info": {"is_vip": false}, "headline": "", "avatar_url": "https://pic1.zhimg.com/da8e974dc_is.jpg", "is_org": false, "gender": -1, "follower_count": 0, "badge": []}, {"is_followed": false, "avatar_url_template": "https://pic3.zhimg.com/v2-b3820ca1c4c48025bd0e304e69958c5a_{size}.jpg", "user_type": "people", "answer_count": 3, "is_following": false, "url_token": "di-shi-ba-ke-cao", "id": "6beedee95a0e43a7a5bb82d80cfddb68", "articles_count": 0, "name": "\u7b2c\u5341\u516b\u68f5\u8349", "is_advertiser": false, "url": "https://www.zhihu.com/people/6beedee95a0e43a7a5bb82d80cfddb68", "type": "people", "vip_info": {"is_vip": false}, "headline": "\u62e7\u87ba\u4e1d\u7231\u597d\u8005", "avatar_url": "https://pic3.zhimg.com/v2-b3820ca1c4c48025bd0e304e69958c5a_is.jpg", "is_org": false, "gender": -1, "follower_count": 601, "badge": []}, {"is_followed": false, "avatar_url_template": "https://pic1.zhimg.com/da8e974dc_{size}.jpg", "user_type": "people", "answer_count": 0, "is_following": false, "url_token": "jmfgjhgdf-80", "id": "6f820139cc5e897116d5a63886e56970", "articles_count": 0, "name": "jmfgjhgdf", "is_advertiser": false, "url": "https://www.zhihu.com/people/6f820139cc5e897116d5a63886e56970", "type": "people", "vip_info": {"is_vip": false}, "headline": "", "avatar_url": "https://pic1.zhimg.com/da8e974dc_is.jpg", "is_org": false, "gender": -1, "follower_count": 0, "badge": []}, {"is_followed": false, "avatar_url_template": "https://pic1.zhimg.com/v2-c2a70a2a2233f232fe04a6b4195907d4_{size}.jpg", "user_type": "people", "answer_count": 6, "is_following": false, "url_token": "jin-mu-yan-90-83", "id": "6d6329547f46d21f22f039efaff3e3ef", "articles_count": 0, "name": "\u91d1\u6728\u7814", "is_advertiser": false, "url": "https://www.zhihu.com/people/6d6329547f46d21f22f039efaff3e3ef", "type": "people", "vip_info": {"is_vip": false}, "headline": "\u5b66\u751f", "avatar_url": "https://pic1.zhimg.com/v2-c2a70a2a2233f232fe04a6b4195907d4_is.jpg", "is_org": false, "gender": -1, "follower_count": 2, "badge": []}, {"is_followed": false, "avatar_url_template": "https://pic1.zhimg.com/da8e974dc_{size}.jpg", "user_type": "people", "answer_count": 0, "is_following": false, "url_token": "shen-hai-xue-yu-bao-43", "id": "b8f50a0627a49d59b651eca669a9a130", "articles_count": 0, "name": "\u6df1\u6d77\u9cd5\u9c7c\u5821", "is_advertiser": false, "url": "https://www.zhihu.com/people/b8f50a0627a49d59b651eca669a9a130", "type": "people", "vip_info": {"is_vip": false}, "headline": "", "avatar_url": "https://pic1.zhimg.com/da8e974dc_is.jpg", "is_org": false, "gender": -1, "follower_count": 0, "badge": []}, {"is_followed": false, "avatar_url_template": "https://pic1.zhimg.com/da8e974dc_{size}.jpg", "user_type": "people", "answer_count": 0, "is_following": false, "url_token": "stanger-94", "id": "a1c303adc4cc0756fdf95e0f9a7dbfbc", "articles_count": 0, "name": "stranger", "is_advertiser": false, "url": "https://www.zhihu.com/people/a1c303adc4cc0756fdf95e0f9a7dbfbc", "type": "people", "vip_info": {"is_vip": false}, "headline": "\u55ef\u54fc", "avatar_url": "https://pic1.zhimg.com/da8e974dc_is.jpg", "is_org": false, "gender": 0, "follower_count": 1, "badge": []}, {"is_followed": false, "avatar_url_template": "https://pic1.zhimg.com/da8e974dc_{size}.jpg", "user_type": "people", "answer_count": 1, "is_following": false, "url_token": "zhou-zhou-85-93-91", "id": "4dabffe82aa6692d2f0bc4d09b1fe758", "articles_count": 0, "name": "\u5468\u5468", "is_advertiser": false, "url": "https://www.zhihu.com/people/4dabffe82aa6692d2f0bc4d09b1fe758", "type": "people", "vip_info": {"is_vip": false}, "headline": "", "avatar_url": "https://pic1.zhimg.com/da8e974dc_is.jpg", "is_org": false, "gender": -1, "follower_count": 0, "badge": []}, {"is_followed": false, "avatar_url_template": "https://pic1.zhimg.com/v2-9b36dc73a4f782ddb57f542185cc8f30_{size}.jpg", "user_type": "people", "answer_count": 93, "is_following": false, "url_token": "wei-ku-19", "id": "915eab0ee2aab3eb999032e1b1124d6f", "articles_count": 0, "name": "\u552f\u82e6", "is_advertiser": false, "url": "https://www.zhihu.com/people/915eab0ee2aab3eb999032e1b1124d6f", "type": "people", "vip_info": {"is_vip": false}, "headline": "BIM\u571f\u6728dnf", "avatar_url": "https://pic1.zhimg.com/v2-9b36dc73a4f782ddb57f542185cc8f30_is.jpg", "is_org": false, "gender": -1, "follower_count": 19, "badge": []}, {"is_followed": false, "avatar_url_template": "https://pic1.zhimg.com/v2-12649bb76a9d12609c9668d405119b58_{size}.jpg", "user_type": "people", "answer_count": 11, "is_following": false, "url_token": "shi-yu-89-7", "id": "050d3f1ab81e13cd4ec458196b1ba50f", "articles_count": 0, "name": "\u840c\u65b0", "is_advertiser": false, "url": "https://www.zhihu.com/people/050d3f1ab81e13cd4ec458196b1ba50f", "type": "people", "vip_info": {"is_vip": false}, "headline": "", "avatar_url": "https://pic1.zhimg.com/v2-12649bb76a9d12609c9668d405119b58_is.jpg", "is_org": false, "gender": 0, "follower_count": 8, "badge": []}, {"is_followed": false, "avatar_url_template": "https://pic1.zhimg.com/da8e974dc_{size}.jpg", "user_type": "people", "answer_count": 9, "is_following": false, "url_token": "shang-shan-da-hu-dui", "id": "e6bbaf7d14521461451c2dbaf812d5a5", "articles_count": 0, "name": "\u4e0a\u5c71\u6253\u864e\u961f", "is_advertiser": false, "url": "https://www.zhihu.com/people/e6bbaf7d14521461451c2dbaf812d5a5", "type": "people", "vip_info": {"is_vip": false}, "headline": "", "avatar_url": "https://pic1.zhimg.com/da8e974dc_is.jpg", "is_org": false, "gender": -1, "follower_count": 0, "badge": []}, {"is_followed": false, "avatar_url_template": "https://pic1.zhimg.com/da8e974dc_{size}.jpg", "user_type": "people", "answer_count": 0, "is_following": false, "url_token": "pa-wu-gui-qi-82", "id": "1f5d6b7244de25d41c73fd834f1c9a95", "articles_count": 0, "name": "\u6015\u65e0\u5f52\u671f", "is_advertiser": false, "url": "https://www.zhihu.com/people/1f5d6b7244de25d41c73fd834f1c9a95", "type": "people", "vip_info": {"is_vip": false}, "headline": "\u6ca1\u6709\u5566", "avatar_url": "https://pic1.zhimg.com/da8e974dc_is.jpg", "is_org": false, "gender": -1, "follower_count": 0, "badge": []}, {"is_followed": false, "avatar_url_template": "https://pic2.zhimg.com/5b694fb3b23c5034978607ff317fd789_{size}.png", "user_type": "people", "answer_count": 0, "is_following": false, "url_token": "sqmbest", "id": "22ee846d927cad5513c17e15a903208a", "articles_count": 0, "name": "dsun", "is_advertiser": false, "url": "https://www.zhihu.com/people/22ee846d927cad5513c17e15a903208a", "type": "people", "vip_info": {"is_vip": false}, "headline": "", "avatar_url": "https://pic2.zhimg.com/5b694fb3b23c5034978607ff317fd789_is.png", "is_org": false, "gender": 1, "follower_count": 2, "badge": []}, {"is_followed": false, "avatar_url_template": "https://pic1.zhimg.com/da8e974dc_{size}.jpg", "user_type": "people", "answer_count": 0, "is_following": false, "url_token": "la-la-he-he-he-95", "id": "5ed65bf216546ff85765e94aae03eacc", "articles_count": 0, "name": "\u5566\u5566\u5475\u5475\u5475", "is_advertiser": false, "url": "https://www.zhihu.com/people/5ed65bf216546ff85765e94aae03eacc", "type": "people", "vip_info": {"is_vip": false}, "headline": "\u5b66\u751f", "avatar_url": "https://pic1.zhimg.com/da8e974dc_is.jpg", "is_org": false, "gender": -1, "follower_count": 0, "badge": []}, {"is_followed": false, "avatar_url_template": "https://pic2.zhimg.com/fc9d692f685df77ac4517ef33ad22701_{size}.jpg", "user_type": "people", "answer_count": 20, "is_following": false, "url_token": "qing-ting-4-10", "id": "6c77fcb1fe7c481a1ab6afc0c01c664f", "articles_count": 0, "name": "\u873b\u8713", "is_advertiser": false, "url": "https://www.zhihu.com/people/6c77fcb1fe7c481a1ab6afc0c01c664f", "type": "people", "vip_info": {"is_vip": false}, "headline": "\u6211\u7231\u73a9\u98de\u76d8\uff0c\u4ec5\u6b64\u800c\u5df2", "avatar_url": "https://pic2.zhimg.com/fc9d692f685df77ac4517ef33ad22701_is.jpg", "is_org": false, "gender": 1, "follower_count": 1, "badge": []}, {"is_followed": false, "avatar_url_template": "https://pic3.zhimg.com/v2-aeaab421e88891f8bcaed1be5c4f0852_{size}.jpg", "user_type": "people", "answer_count": 25, "is_following": false, "url_token": "ke-li-si-di-ya-nuo-67", "id": "8afa6da76972e3fcb6f31b168b9588a4", "articles_count": 0, "name": "Unique", "is_advertiser": false, "url": "https://www.zhihu.com/people/8afa6da76972e3fcb6f31b168b9588a4", "type": "people", "vip_info": {"is_vip": false}, "headline": "\u7687\u5bb6\u79cd\u5730\u5927\u5b66\u673a\u68b0\u72d7\u4e00\u679a", "avatar_url": "https://pic3.zhimg.com/v2-aeaab421e88891f8bcaed1be5c4f0852_is.jpg", "is_org": false, "gender": 1, "follower_count": 21, "badge": []}, {"is_followed": false, "avatar_url_template": "https://pic4.zhimg.com/v2-44e331559e7c2b3591c8b4a68f738d87_{size}.jpg", "user_type": "people", "answer_count": 4, "is_following": false, "url_token": "zhe-xue-de-wei-xiao-5", "id": "6052080c6e68f04f78e54350c5c24a3e", "articles_count": 0, "name": "\u54f2\u5b66\u7684\u5fae\u7b11", "is_advertiser": false, "url": "https://www.zhihu.com/people/6052080c6e68f04f78e54350c5c24a3e", "type": "people", "vip_info": {"is_vip": false}, "headline": "\u56fd\u9645\u8457\u540d\u7535\u5f71\u7535\u89c6\u5267\u89c2\u4f17", "avatar_url": "https://pic4.zhimg.com/v2-44e331559e7c2b3591c8b4a68f738d87_is.jpg", "is_org": false, "gender": -1, "follower_count": 0, "badge": []}, {"is_followed": false, "avatar_url_template": "https://pic1.zhimg.com/da8e974dc_{size}.jpg", "user_type": "people", "answer_count": 7, "is_following": false, "url_token": "silence9705", "id": "0d4247fc5eed577d89dcb4fee17f7e35", "articles_count": 0, "name": "\u6211\u4e0d\u662f\u5927\u4f6c7", "is_advertiser": false, "url": "https://www.zhihu.com/people/0d4247fc5eed577d89dcb4fee17f7e35", "type": "people", "vip_info": {"is_vip": false}, "headline": "", "avatar_url": "https://pic1.zhimg.com/da8e974dc_is.jpg", "is_org": false, "gender": -1, "follower_count": 1, "badge": []}, {"is_followed": false, "avatar_url_template": "https://pic3.zhimg.com/450812e15fe2116e8010acabbf3ca88e_{size}.jpg", "user_type": "people", "answer_count": 0, "is_following": false, "url_token": "wang-lin-peng-10", "id": "c0d35b50a848b5c659696884cd075ab1", "articles_count": 0, "name": "\u738b\u6797\u9e4f", "is_advertiser": false, "url": "https://www.zhihu.com/people/c0d35b50a848b5c659696884cd075ab1", "type": "people", "vip_info": {"is_vip": false}, "headline": "\u6c7d\u8f66\u7ef4\u4fee", "avatar_url": "https://pic3.zhimg.com/450812e15fe2116e8010acabbf3ca88e_is.jpg", "is_org": false, "gender": -1, "follower_count": 0, "badge": []}]}